nyfedapi/__init__.py
nyfedapi/ambs/__init__.py
nyfedapi/fxs/__init__.py
nyfedapi/guidesheets/__init__.py
nyfedapi/marketshare/__init__.py
nyfedapi/pd/__init__.py
nyfedapi/rates/__init__.py
nyfedapi/rp/__init__.py
nyfedapi/seclending/__init__.py
nyfedapi/soma/__init__.py
nyfedapi/tsy/__init__.py
nyfedapi-0.0.1.dist-info/LICENSE
nyfedapi-0.0.1.dist-info/METADATA
nyfedapi-0.0.1.dist-info/WHEEL
nyfedapi-0.0.1.dist-info/top_level.txt
nyfedapi-0.0.1.dist-info/RECORD
