Metadata-Version: 2.1
Name: nyfedapi
Version: 0.0.1
Summary: A Python wrapper to easily retrieve data from the Federal Reserve Bank of New York (FRBoNY) official API in pandas format.
Home-page: https://github.com/Jaldekoa/nyfedapi
Author: Jon Aldekoa
Author-email: jaldekoa@gmail.com
License: MIT License
Platform: Any
Classifier: Development Status :: 3 - Alpha
Classifier: Intended Audience :: Education
Classifier: Intended Audience :: Financial and Insurance Industry
Classifier: Intended Audience :: Science/Research
Classifier: Programming Language :: Python
Classifier: Programming Language :: Python :: 3
Classifier: Operating System :: OS Independent
Classifier: Programming Language :: Python :: 3.9
Classifier: Programming Language :: Python :: 3.10
Classifier: Programming Language :: Python :: 3.11
Classifier: Programming Language :: Python :: 3.12
Classifier: License :: OSI Approved :: MIT License
License-File: LICENSE
Requires-Dist: setuptools >=68.2
Requires-Dist: pandas >=2.0.0
Requires-Dist: requests >=2.23.0
